uav4res/Cell.py
uav4res/DemoState.py
uav4res/Game.py
uav4res/Map.py
uav4res/MenuState.py
uav4res/Swarm.py
uav4res/SwarmManager.py
uav4res/Uav.py
uav4res/__init__.py
uav4res/__main__.py
uav4res/config.py
uav4res/assets/images/uav.png
uav4res/engine/Button.py
uav4res/engine/GameState.py
uav4res/engine/GameStateManager.py
uav4res/engine/InputManager.py
uav4res/engine/Singleton.py
uav4res/engine/SoundManager.py
uav4res/engine/TextManager.py
uav4res/engine/TextureManager.py
uav4res/engine/Window.py
uav4res/engine/__init__.py
uav4res/engine/__pycache__/Button.cpython-312.pyc
uav4res/engine/__pycache__/GameState.cpython-312.pyc
uav4res/engine/__pycache__/GameStateManager.cpython-312.pyc
uav4res/engine/__pycache__/InputManager.cpython-312.pyc
uav4res/engine/__pycache__/Singleton.cpython-312.pyc
uav4res/engine/__pycache__/TextManager.cpython-312.pyc
uav4res/engine/__pycache__/TextureManager.cpython-312.pyc
uav4res/engine/__pycache__/Window.cpython-312.pyc
uav4res/engine/__pycache__/__init__.cpython-312.pyc
uav4res-0.2.2.dist-info/LICENSE
uav4res-0.2.2.dist-info/METADATA
uav4res-0.2.2.dist-info/WHEEL
uav4res-0.2.2.dist-info/entry_points.txt
uav4res-0.2.2.dist-info/top_level.txt
uav4res-0.2.2.dist-info/RECORD
