Metadata-Version: 2.2
Name: uav4res
Version: 0.2.2
Summary: uav4res
Home-page: https://github.com/png261/meoww
Download-URL: https://github.com/png261/meoww/archive/0.2.2.tar.gz
Author: Phuong Nguyen
Author-email: nhphuong.code@gmail.com
License: MIT
Keywords: uav4res
Classifier: Environment :: X11 Applications
Classifier: License :: OSI Approved :: MIT License
Classifier: Operating System :: POSIX :: Linux
Classifier: Programming Language :: Python :: 3.5
Classifier: Programming Language :: Python :: 3.6
Requires-Python: >=3.5
License-File: LICENSE
Requires-Dist: pygame>=2.4.0
Requires-Dist: scikit-learn
Requires-Dist: numpy
Dynamic: author
Dynamic: author-email
Dynamic: classifier
Dynamic: description
Dynamic: description-content-type
Dynamic: download-url
Dynamic: home-page
Dynamic: keywords
Dynamic: license
Dynamic: requires-dist
Dynamic: requires-python
Dynamic: summary
